wagtail_django_recaptcha-0.1.dist-info/DESCRIPTION.rst
wagtail_django_recaptcha-0.1.dist-info/METADATA
wagtail_django_recaptcha-0.1.dist-info/RECORD
wagtail_django_recaptcha-0.1.dist-info/WHEEL
wagtail_django_recaptcha-0.1.dist-info/metadata.json
wagtail_django_recaptcha-0.1.dist-info/top_level.txt
wagtailcaptcha/__init__.py
wagtailcaptcha/forms.py
wagtailcaptcha/models.py
