Metadata-Version: 2.0
Name: wagtail-django-recaptcha
Version: 0.1
Summary: A simple recaptcha field for Wagtail Form Pages.
Home-page: http://github.com/springload/wagtail-django-recaptcha
Author: Jordi J. Tablada
Author-email: jordi@springload.co.nz
License: BSD License
Platform: UNKNOWN
Classifier: Environment :: Web Environment
Classifier: Framework :: Django
Classifier: Intended Audience :: Developers
Classifier: License :: OSI Approved :: BSD License
Classifier: Operating System :: OS Independent
Classifier: Programming Language :: Python
Classifier: Topic :: Internet :: WWW/HTTP
Classifier: Topic :: Internet :: WWW/HTTP :: Dynamic Content
Requires-Dist: django-recaptcha
